planetary_test_data/__init__.py
planetary_test_data/data.json
planetary_test_data/planetary_test_data.py
planetary_test_data-0.4.0.dist-info/DESCRIPTION.rst
planetary_test_data-0.4.0.dist-info/METADATA
planetary_test_data-0.4.0.dist-info/RECORD
planetary_test_data-0.4.0.dist-info/WHEEL
planetary_test_data-0.4.0.dist-info/entry_points.txt
planetary_test_data-0.4.0.dist-info/metadata.json
planetary_test_data-0.4.0.dist-info/top_level.txt
