Metadata-Version: 2.0
Name: planetary-test-data
Version: 0.4.0
Summary: Planetary Test Data contains a list of planetary data for software testing purposes and utilities to retrieve them.
Home-page: https://github.com/planetarypy/planetary_test_data
Author: PlanetaryPy Developers
Author-email: contact@planetarypy.com
License: BSD
Keywords: planetary_test_data
Platform: UNKNOWN
Classifier: Development Status :: 2 - Pre-Alpha
Classifier: Intended Audience :: Developers
Classifier: License :: OSI Approved :: BSD License
Classifier: Natural Language :: English
Classifier: Programming Language :: Python :: 2
Classifier: Programming Language :: Python :: 2.6
Classifier: Programming Language :: Python :: 2.7
Classifier: Programming Language :: Python :: 3
Classifier: Programming Language :: Python :: 3.3
Classifier: Programming Language :: Python :: 3.4
